sphinx_ahd_theme/__init__.py
sphinx_ahd_theme/breadcrumbs.html
sphinx_ahd_theme/domainindex.html
sphinx_ahd_theme/extensions.html
sphinx_ahd_theme/footer.html
sphinx_ahd_theme/genindex-single.html
sphinx_ahd_theme/genindex-split.html
sphinx_ahd_theme/genindex.html
sphinx_ahd_theme/globaltoc.html
sphinx_ahd_theme/layout.html
sphinx_ahd_theme/page.html
sphinx_ahd_theme/pager.html
sphinx_ahd_theme/search.html
sphinx_ahd_theme/searchresults.html
sphinx_ahd_theme/sitemap.html
sphinx_ahd_theme/source-buttons.html
sphinx_ahd_theme/theme.conf
sphinx_ahd_theme/static/dist/fontawesome.css
sphinx_ahd_theme/static/dist/fontawesome.css.map
sphinx_ahd_theme/static/dist/fontawesome.js
sphinx_ahd_theme/static/dist/theme.css
sphinx_ahd_theme/static/dist/theme.css.map
sphinx_ahd_theme/static/dist/theme.js
sphinx_ahd_theme/static/dist/theme.js.map
sphinx_ahd_theme/static/dist/vendor.js
sphinx_ahd_theme/static/dist/vendor.js.LICENSE.txt
sphinx_ahd_theme/static/dist/vendor.js.map
sphinx_ahd_theme/static/dist/assets/fa-brands-400.eot
sphinx_ahd_theme/static/dist/assets/fa-brands-400.svg
sphinx_ahd_theme/static/dist/assets/fa-brands-400.ttf
sphinx_ahd_theme/static/dist/assets/fa-brands-400.woff
sphinx_ahd_theme/static/dist/assets/fa-brands-400.woff2
sphinx_ahd_theme/static/dist/assets/fa-regular-400.eot
sphinx_ahd_theme/static/dist/assets/fa-regular-400.svg
sphinx_ahd_theme/static/dist/assets/fa-regular-400.ttf
sphinx_ahd_theme/static/dist/assets/fa-regular-400.woff
sphinx_ahd_theme/static/dist/assets/fa-regular-400.woff2
sphinx_ahd_theme/static/dist/assets/fa-solid-900.eot
sphinx_ahd_theme/static/dist/assets/fa-solid-900.svg
sphinx_ahd_theme/static/dist/assets/fa-solid-900.ttf
sphinx_ahd_theme/static/dist/assets/fa-solid-900.woff
sphinx_ahd_theme/static/dist/assets/fa-solid-900.woff2
sphinx_ahd_theme/static/img/ahd-logo-new.svg
tests/__init__.py
tests/test_python_sphinx_ahd_theme.py
tests/test_visual_regression.py
sphinx_ahd_theme-5.3.8.dist-info/METADATA
sphinx_ahd_theme-5.3.8.dist-info/WHEEL
sphinx_ahd_theme-5.3.8.dist-info/top_level.txt
sphinx_ahd_theme-5.3.8.dist-info/RECORD
