Metadata-Version: 2.1
Name: sphinx-ahd-theme
Version: 5.3.8
Summary: Sphinx AHDCreative Theme
Home-page: https://github.com/ahdcreative/sphinx_ahd_theme
Author: AHDCreative
Author-email: hello@ahd-creative.agency
Classifier: Framework :: Sphinx
Classifier: Framework :: Sphinx :: Theme
Classifier: Development Status :: 5 - Production/Stable
Classifier: License :: OSI Approved :: MIT License
Classifier: Intended Audience :: Developers
Classifier: Programming Language :: Python :: 3.6
Classifier: Programming Language :: Python :: 3.7
Classifier: Programming Language :: Python :: 3.8
Classifier: Operating System :: OS Independent
Classifier: Topic :: Documentation
Classifier: Topic :: Software Development :: Documentation
Requires-Python: >=3.6
